avlos/__init__.py
avlos/_version.py
avlos/bitmask_field.py
avlos/channel.py
avlos/cli.py
avlos/counter.py
avlos/datatypes.py
avlos/deserializer.py
avlos/enum_field.py
avlos/formatting.py
avlos/json_codec.py
avlos/processor.py
avlos/unit_field.py
avlos/validation.py
avlos/definitions/__init__.py
avlos/definitions/remote_attribute.py
avlos/definitions/remote_bitmask.py
avlos/definitions/remote_enum.py
avlos/definitions/remote_function.py
avlos/definitions/remote_node.py
avlos/definitions/remote_root_node.py
avlos/generators/__init__.py
avlos/generators/filters.py
avlos/generators/generator_c.py
avlos/generators/generator_cpp.py
avlos/generators/generator_dbc.py
avlos/generators/generator_rst.py
avlos/mixins/__init__.py
avlos/mixins/comm_node.py
avlos/mixins/func_attr_node.py
avlos/mixins/impex_node.py
avlos/mixins/meta_node.py
avlos/mixins/named_node.py
avlos/templates/device.cpp.jinja
avlos/templates/device.dbc.jinja
avlos/templates/device.hpp.jinja
avlos/templates/docs.rst.jinja
avlos/templates/fw_endpoints.c.jinja
avlos/templates/fw_endpoints.h.jinja
avlos/templates/remote_object.cpp.jinja
avlos/templates/remote_object.hpp.jinja
avlos/templates/tm_enums.h.jinja
avlos/templates/tm_helpers.hpp.jinja
avlos-0.9.0.dist-info/licenses/LICENSE
avlos-0.9.0.dist-info/METADATA
avlos-0.9.0.dist-info/WHEEL
avlos-0.9.0.dist-info/entry_points.txt
avlos-0.9.0.dist-info/top_level.txt
avlos-0.9.0.dist-info/RECORD
