Metadata-Version: 2.4
Name: Avlos
Version: 0.9.0
Summary: Generate type-safe communication protocols for embedded systems from a single YAML specification
Home-page: https://www.tinymovr.com
Author: Yannis Chatzikonstantinou
Author-email: yannis@tinymovr.com
Requires-Python: >=3.9
License-File: LICENSE
Requires-Dist: marshmallow
Requires-Dist: pyyaml
Requires-Dist: pint
Requires-Dist: docopt
Requires-Dist: jinja2
Provides-Extra: dev
Requires-Dist: rstcheck; extra == "dev"
Dynamic: author
Dynamic: author-email
Dynamic: description
Dynamic: description-content-type
Dynamic: home-page
Dynamic: license-file
Dynamic: provides-extra
Dynamic: requires-dist
Dynamic: requires-python
Dynamic: summary
